{"stem":"begriffnen","instances":[{"docId":"entry__1928-11-11","docUri":"entry__1928-11-11.html","score":1,"contexts":[{"form":"begriffnen","weight":"1","pos":16,"context":"...11\/11 S.― Holte C. P. aus der im Entstehen <mark>begriffnen<\/mark> neuen Wohnung; fuhren Cobenzl; spazierten über Krapfenwaldl...","fid":"page"}]},{"docId":"entry__1914-06-08","docUri":"entry__1914-06-08.html","score":1,"contexts":[{"form":"begriffnen","weight":"1","pos":20,"context":"...unter der Hängeesche erzählt er von seinem im Bau <mark>begriffnen<\/mark> Haus, der neuen Jugend, den Theosophen,...","fid":"page"}]}]}