{"stem":"beschimpften","instances":[{"docId":"entry__1907-04-05","docUri":"entry__1907-04-05.html","score":1,"contexts":[{"form":"beschimpften","weight":"1","pos":104,"context":"...Die andern Leute verdienen wenigstens Geld; die viel <mark>beschimpften<\/mark> wie Sudermann, Fulda, Blumenthal, Kadelburg verdienen...","fid":"page"}]},{"docId":"entry__1894-04-23","docUri":"entry__1894-04-23.html","score":1,"contexts":[{"form":"Beschimpften","weight":"1","pos":21,"context":"Abds. bei Dilly bis 3. <mark>Beschimpften<\/mark> uns gegenseitig.―","fid":"page"}]}]}