{"stem":"bruckner","instances":[{"docId":"entry__1904-11-12","docUri":"entry__1904-11-12.html","score":1,"contexts":[{"form":"Bruckner","weight":"1","pos":18,"context":"Bei Mama. 4hd. <mark>Bruckner<\/mark> 7te.","fid":"page"}]},{"docId":"entry__1917-02-23","docUri":"entry__1917-02-23.html","score":1,"contexts":[{"form":"Bruckner","weight":"1","pos":22,"context":"Nm. mit Vicki <mark>Bruckner<\/mark> Achte.―","fid":"page"}]},{"docId":"entry__1905-12-02","docUri":"entry__1905-12-02.html","score":1,"contexts":[{"form":"Bruckner","weight":"1","pos":22,"context":"...Bei Mama zu Tisch. Nm. mit ihr IX. <mark>Bruckner<\/mark>.―","fid":"page"}]},{"docId":"entry__1907-01-05","docUri":"entry__1907-01-05.html","score":1,"contexts":[{"form":"Bruckner","weight":"1","pos":51,"context":"Mit Mama Nm. II. <mark>Bruckner<\/mark>.―","fid":"page"}]},{"docId":"entry__1919-04-14","docUri":"entry__1919-04-14.html","score":1,"contexts":[{"form":"Bruckner","weight":"1","pos":26,"context":"Mit Heini <mark>Bruckner<\/mark> Neunte.","fid":"page"}]},{"docId":"entry__1917-10-16","docUri":"entry__1917-10-16.html","score":1,"contexts":[{"form":"Bruckner","weight":"1","pos":46,"context":"Mit Heini <mark>Bruckner<\/mark> Neunte. Sein musik. Interesse und Talent entwickelt sich...","fid":"page"}]},{"docId":"entry__1905-03-21","docUri":"entry__1905-03-21.html","score":1,"contexts":[{"form":"Bruckner","weight":"1","pos":24,"context":"...Wilheim, mit O. und Liesl. Mit Mama <mark>Bruckner<\/mark> I.―","fid":"page"}]},{"docId":"entry__1908-03-03","docUri":"entry__1908-03-03.html","score":1,"contexts":[{"form":"Bruckner","weight":"1","pos":22,"context":"Bei Mama zu Tisch. <mark>Bruckner<\/mark> Zweite.","fid":"page"}]},{"docId":"entry__1916-09-20","docUri":"entry__1916-09-20.html","score":1,"contexts":[{"form":"Bruckner","weight":"1","pos":29,"context":"Mit Gerty L. <mark>Bruckner<\/mark> fünfte.―","fid":"page"}]},{"docId":"entry__1914-03-14","docUri":"entry__1914-03-14.html","score":1,"contexts":[{"form":"Bruckner","weight":"1","pos":33,"context":"...Fritz Zuckerkandl, mit dem ich 2 Sätze der <mark>Bruckner<\/mark> 104 1914: III 14 - III 19 IV....","fid":"page"}]},{"docId":"entry__1912-11-15","docUri":"entry__1912-11-15.html","score":1,"contexts":[{"form":"Bruckners","weight":"1","pos":27,"context":"Viki Z. zu Tisch; mit ihm <mark>Bruckners<\/mark> Neunte.","fid":"page"}]},{"docId":"entry__1921-12-13","docUri":"entry__1921-12-13.html","score":1,"contexts":[{"form":"Bruckner","weight":"1","pos":38,"context":"― Mit Heini <mark>Bruckner<\/mark> Vierte.","fid":"page"}]},{"docId":"entry__1930-12-07","docUri":"entry__1930-12-07.html","score":1,"contexts":[{"form":"Bruckner","weight":"1","pos":34,"context":"...Gegen 6 M. Mauprey (Paris, Übersetzer von <mark>Bruckner<\/mark> etc.) ― wegen Bernhardi fürs Odéon (Dir. Abram...","fid":"page"}]},{"docId":"entry__1906-11-07","docUri":"entry__1906-11-07.html","score":1,"contexts":[{"form":"Bruckner","weight":"1","pos":25,"context":"Mit O. im Gesellschafts Concert: <mark>Bruckner<\/mark>.―","fid":"page"}]},{"docId":"entry__1904-10-27","docUri":"entry__1904-10-27.html","score":1,"contexts":[{"form":"Bruckner","weight":"1","pos":23,"context":"Mit ihr Nm. 4hd. 8.te <mark>Bruckner<\/mark>.―","fid":"page"}]},{"docId":"entry__1920-05-16","docUri":"entry__1920-05-16.html","score":1,"contexts":[{"form":"Bruckner","weight":"1","pos":34,"context":"...spiele nach Tisch mit Heini auswendig 4händig falschen <mark>Bruckner<\/mark> u. dergl.―","fid":"page"}]},{"docId":"entry__1930-12-27","docUri":"entry__1930-12-27.html","score":1,"contexts":[{"form":"Bruckner","weight":"1","pos":52,"context":"Mit C. P. Volksth., <mark>Bruckner<\/mark> (Tagger) Elisabeth; auf niedrerm Niveau als...","fid":"page"}]},{"docId":"entry__1906-12-16","docUri":"entry__1906-12-16.html","score":1,"contexts":[{"form":"Bruckner","weight":"1","pos":19,"context":"Nm. mit Mama 6. <mark>Bruckner<\/mark>.―","fid":"page"}]},{"docId":"entry__1928-07-09","docUri":"entry__1928-07-09.html","score":1,"contexts":[{"form":"Bruckner","weight":"1","pos":29,"context":"Las ein Stück von <mark>Bruckner<\/mark>, junger Autor (soll ein begabtes Stück geschrieben haben...","fid":"page"}]},{"docId":"entry__1919-02-15","docUri":"entry__1919-02-15.html","score":1,"contexts":[{"form":"Bruckner","weight":"1","pos":93,"context":"Mit Heini <mark>Bruckner<\/mark> Dritte.―","fid":"page"}]},{"docId":"entry__1917-03-11","docUri":"entry__1917-03-11.html","score":1,"contexts":[{"form":"Bruckner","weight":"1","pos":34,"context":"...Mit Heini Tonkünstler Orch. (Juan Reyes, <mark>Bruckner<\/mark> V.).","fid":"page"}]},{"docId":"entry__1917-08-31","docUri":"entry__1917-08-31.html","score":1,"contexts":[{"form":"Bruckner","weight":"1","pos":27,"context":"...der Fldb. Scene.― Mit Gerty v. Landesberger <mark>Bruckner<\/mark> Dritte. Heini, und Franzi Stern als Publikum;...","fid":"page"}]},{"docId":"entry__1923-01-28","docUri":"entry__1923-01-28.html","score":1,"contexts":[{"form":"Bruckner","weight":"1","pos":26,"context":"Mit Heini <mark>Bruckner<\/mark> Dritte.","fid":"page"}]},{"docId":"entry__1929-04-29","docUri":"entry__1929-04-29.html","score":1,"contexts":[{"form":"Bruckner","weight":"1","pos":48,"context":"Mit C. P. Josefstadt ― <mark>Bruckner<\/mark> (der Anonymus), Verbrecher: ― habe dem Stück...","fid":"page"}]},{"docId":"entry__1918-08-19","docUri":"entry__1918-08-19.html","score":1,"contexts":[{"form":"Bruckner","weight":"1","pos":41,"context":"Z. N. Vicki; <mark>Bruckner<\/mark> Dritte mit ihm.―","fid":"page"}]},{"docId":"entry__1906-10-04","docUri":"entry__1906-10-04.html","score":1,"contexts":[{"form":"Bruckner","weight":"1","pos":20,"context":"Mit Mama Nm. bei uns <mark>Bruckner<\/mark> V.―","fid":"page"}]},{"docId":"entry__1917-03-09","docUri":"entry__1917-03-09.html","score":1,"contexts":[{"form":"Bruckner","weight":"1","pos":83,"context":"Mit Heini <mark>Bruckner<\/mark> Fünfte. Wits Lebensroman ausgelesen.―","fid":"page"}]},{"docId":"entry__1922-10-15","docUri":"entry__1922-10-15.html","score":1,"contexts":[{"form":"Bruckner","weight":"1","pos":31,"context":"Mit Heini Nm.: Goldmark; Italienouverture;― <mark>Bruckner<\/mark> Erste,― Beethoven, Weihe des Hauses.―","fid":"page"}]},{"docId":"entry__1905-04-06","docUri":"entry__1905-04-06.html","score":1,"contexts":[{"form":"Bruckner","weight":"1","pos":22,"context":"...O. und Frl. Lubelsky, spielte mit Mama <mark>Bruckner<\/mark> VIII.","fid":"page"}]},{"docId":"entry__1905-03-02","docUri":"entry__1905-03-02.html","score":1,"contexts":[{"form":"Bruckner","weight":"1","pos":24,"context":"Mit Mama Nachm. begonnen <mark>Bruckner<\/mark> V.; durch Gespräch mit O. über Liesl unterbrochen.―...","fid":"page"}]},{"docId":"entry__1907-11-17","docUri":"entry__1907-11-17.html","score":1,"contexts":[{"form":"Bruckner","weight":"1","pos":43,"context":"Mit Mama <mark>Bruckner<\/mark> III.―","fid":"page"}]},{"docId":"entry__1909-04-14","docUri":"entry__1909-04-14.html","score":1,"contexts":[{"form":"Bruckner","weight":"1","pos":16,"context":"14\/4 Zu Tisch Mama da. <mark>Bruckner<\/mark> Fünfte.―","fid":"page"}]},{"docId":"entry__1912-04-17","docUri":"entry__1912-04-17.html","score":1,"contexts":[{"form":"Bruckner","weight":"1","pos":26,"context":"...hier. Mit Felix 1. Satz Mahler II. und Beginn <mark>Bruckner<\/mark> III.; dann mit ihm und Andrée übern Ring...","fid":"page"}]},{"docId":"entry__1930-11-14","docUri":"entry__1930-11-14.html","score":1,"contexts":[{"form":"Bruckner","weight":"1","pos":77,"context":"...O. Dtsch. Theater „Elisabeth“ von Tagger (<mark>Bruckner<\/mark>) mit der Straub und Krausz. Sehr starker...","fid":"page"}]},{"docId":"entry__1906-01-14","docUri":"entry__1906-01-14.html","score":1,"contexts":[{"form":"Bruckner","weight":"1","pos":69,"context":"..., Benedikt), Rob. Hirschfeld (Weissagung, <mark>Bruckner<\/mark>), Lothar (Harlekin in London), Bahr (...","fid":"page"}]},{"docId":"entry__1917-04-21","docUri":"entry__1917-04-21.html","score":1,"contexts":[{"form":"Bruckner","weight":"1","pos":33,"context":"Mit Heini <mark>Bruckner<\/mark> Dritte.―","fid":"page"}]},{"docId":"entry__1917-07-02","docUri":"entry__1917-07-02.html","score":1,"contexts":[{"form":"Bruckner","weight":"1","pos":24,"context":"Mit Heini <mark>Bruckner<\/mark> Zweite (schön aber dumm).","fid":"page"}]},{"docId":"entry__1917-11-25","docUri":"entry__1917-11-25.html","score":1,"contexts":[{"form":"Bruckner","weight":"1","pos":21,"context":"...Baumeister Trauerfeier. Millenkovich hielt eine banale Rede; <mark>Bruckner<\/mark> Adagio.―","fid":"page"}]},{"docId":"entry__1907-01-20","docUri":"entry__1907-01-20.html","score":1,"contexts":[{"form":"Bruckner","weight":"1","pos":36,"context":"Mittag bei Mama. Mit Raoul die 8. <mark>Bruckner<\/mark>.","fid":"page"}]},{"docId":"entry__1907-11-23","docUri":"entry__1907-11-23.html","score":1,"contexts":[{"form":"Bruckner","weight":"1","pos":44,"context":"...ihr Wesen durch die Musik ausdrücken (im Gegensatz zu <mark>Bruckner<\/mark>, der einfach wunderbare Musik von sich gibt); ergreifend...","fid":"page"}]},{"docId":"entry__1914-06-14","docUri":"entry__1914-06-14.html","score":1,"contexts":[{"form":"Bruckner","weight":"1","pos":47,"context":"...Loewe sangen, auch Wolf. Loewe spielte auswendig <mark>Bruckner<\/mark> 8., 1. und 2. Satz ― unvergleichlich.―","fid":"page"}]},{"docId":"entry__1914-10-02","docUri":"entry__1914-10-02.html","score":1,"contexts":[{"form":"Bruckner","weight":"1","pos":26,"context":"Mit Vicki <mark>Bruckner<\/mark> Achte.―","fid":"page"}]},{"docId":"entry__1917-08-24","docUri":"entry__1917-08-24.html","score":1,"contexts":[{"form":"Bruckner","weight":"1","pos":20,"context":"Mit Heini <mark>Bruckner<\/mark> Achte.","fid":"page"}]},{"docId":"entry__1913-09-28","docUri":"entry__1913-09-28.html","score":1,"contexts":[{"form":"Bruckner","weight":"1","pos":20,"context":"Zu Tisch Vicki. Mit ihm <mark>Bruckner<\/mark> V. und ein Haendelconcert.― Hr. und Frau Dr....","fid":"page"}]},{"docId":"entry__1923-05-04","docUri":"entry__1923-05-04.html","score":1,"contexts":[{"form":"Bruckner","weight":"1","pos":49,"context":"Nm. mit Heini die Romantische von <mark>Bruckner<\/mark>.","fid":"page"}]},{"docId":"entry__1929-04-19","docUri":"entry__1929-04-19.html","score":1,"contexts":[{"form":"Bruckner","weight":"1","pos":73,"context":"...gestrige Erfolg der „Verbrecher“ (von dem pseud. <mark>Bruckner<\/mark>).― Die Hofr. erzählt von Reinh.s Hollywooderlebnissen...","fid":"page"}]},{"docId":"entry__1908-12-21","docUri":"entry__1908-12-21.html","score":1,"contexts":[{"form":"Bruckner","weight":"1","pos":25,"context":"...Quartetts. An Schönberg glaub ich nicht. Ich habe <mark>Bruckner<\/mark>, Mahler gleich verstanden ― sollt ich jetzt versagen...","fid":"page"}]},{"docId":"entry__1917-04-23","docUri":"entry__1917-04-23.html","score":1,"contexts":[{"form":"Bruckner","weight":"1","pos":19,"context":"Vicki zum Thee und z. N.― <mark>Bruckner<\/mark> erste mit ihm.","fid":"page"}]},{"docId":"entry__1910-02-13","docUri":"entry__1910-02-13.html","score":1,"contexts":[{"form":"Bruckner","weight":"1","pos":25,"context":"Nm. mit Mama bei uns <mark>Bruckner<\/mark> III.","fid":"page"}]},{"docId":"entry__1930-02-28","docUri":"entry__1930-02-28.html","score":1,"contexts":[{"form":"Bruckner“s","weight":"1","pos":33,"context":"Nm. las ich Ferd. „<mark>Bruckner“s<\/mark> „Creatur“.― Gewiss das was man „Talent“...","fid":"page"}]},{"docId":"entry__1907-03-22","docUri":"entry__1907-03-22.html","score":1,"contexts":[{"form":"Bruckner","weight":"1","pos":31,"context":"― Mit Mama Nm. <mark>Bruckner<\/mark> Romantische.","fid":"page"}]},{"docId":"entry__1910-11-12","docUri":"entry__1910-11-12.html","score":1,"contexts":[{"form":"Bruckner","weight":"1","pos":93,"context":"...Julius Helene; Gustav. Mit Mama das Adagio <mark>Bruckner<\/mark> VII.―","fid":"page"}]},{"docId":"entry__1918-03-03","docUri":"entry__1918-03-03.html","score":1,"contexts":[{"form":"Bruckner","weight":"1","pos":26,"context":"Mit Heini <mark>Bruckner<\/mark> Sechste.","fid":"page"}]},{"docId":"entry__1921-11-10","docUri":"entry__1921-11-10.html","score":1,"contexts":[{"form":"Bruckner","weight":"1","pos":20,"context":"Tonk.-Concert (Furtwängler) <mark>Bruckner<\/mark> 8.―","fid":"page"}]},{"docId":"entry__1910-04-05","docUri":"entry__1910-04-05.html","score":1,"contexts":[{"form":"Bruckner","weight":"1","pos":39,"context":"Bei Mama zu Tisch. <mark>Bruckner<\/mark> 8te.","fid":"page"}]},{"docId":"entry__1916-09-23","docUri":"entry__1916-09-23.html","score":1,"contexts":[{"form":"Bruckner","weight":"1","pos":41,"context":"Mit Gerty L. <mark>Bruckner<\/mark> achte. Das Wort Mahlers halb ein Genie halb ein...","fid":"page"}]},{"docId":"entry__1916-09-22","docUri":"entry__1916-09-22.html","score":1,"contexts":[{"form":"Bruckner","weight":"1","pos":17,"context":"22\/9 Regen, Kälte.― Mit Gerty L. <mark>Bruckner<\/mark> Siebente.","fid":"page"}]},{"docId":"entry__1913-03-20","docUri":"entry__1913-03-20.html","score":1,"contexts":[{"form":"Bruckner","weight":"1","pos":25,"context":"...Buben, die über Tisch blieben. Mit Hans <mark>Bruckner<\/mark> Achte.―","fid":"page"}]},{"docId":"entry__1917-03-21","docUri":"entry__1917-03-21.html","score":1,"contexts":[{"form":"Bruckner","weight":"1","pos":19,"context":"Zum Nachtm. Vicki, mit ihm <mark>Bruckner<\/mark> 9., Bach Prel. und Fuge. Gespräch über...","fid":"page"}]},{"docId":"entry__1905-12-19","docUri":"entry__1905-12-19.html","score":1,"contexts":[{"form":"Bruckner","weight":"1","pos":21,"context":"....― Sprach Richard Horn (über Mahler, Brahms, <mark>Bruckner<\/mark>) nach langer Zeit; dann Theo Baumgarten (über Bahr...","fid":"page"}]},{"docId":"entry__1906-03-15","docUri":"entry__1906-03-15.html","score":1,"contexts":[{"form":"Bruckner","weight":"1","pos":36,"context":"Mit Mama Nm. 8. <mark>Bruckner<\/mark> Symphonie.―","fid":"page"}]},{"docId":"entry__1909-02-16","docUri":"entry__1909-02-16.html","score":1,"contexts":[{"form":"Bruckner","weight":"1","pos":48,"context":"Nm. mit Mama 3. <mark>Bruckner<\/mark>.","fid":"page"}]},{"docId":"entry__1888-01-22","docUri":"entry__1888-01-22.html","score":1,"contexts":[{"form":"Bruckner","weight":"1","pos":17,"context":"22\/1 Sonntag. Mittag Conc. <mark>Bruckner<\/mark>. Cohns.","fid":"page"}]},{"docId":"entry__1907-10-20","docUri":"entry__1907-10-20.html","score":1,"contexts":[{"form":"Bruckner","weight":"1","pos":16,"context":"Nm. mit Mama <mark>Bruckner<\/mark> Fünfte.―","fid":"page"}]},{"docId":"entry__1908-03-08","docUri":"entry__1908-03-08.html","score":1,"contexts":[{"form":"Bruckner","weight":"1","pos":18,"context":"Nm. Agnes Speyer da; mit ihr <mark>Bruckner<\/mark> Vierte.","fid":"page"}]},{"docId":"entry__1906-01-18","docUri":"entry__1906-01-18.html","score":1,"contexts":[{"form":"Bruckner","weight":"1","pos":19,"context":"Bei Mama gegessen. III. <mark>Bruckner<\/mark>.―","fid":"page"}]},{"docId":"entry__1920-06-13","docUri":"entry__1920-06-13.html","score":1,"contexts":[{"form":"Bruckner","weight":"1","pos":68,"context":"...Mit Heini (dessen schriftl. Matura morgen beginnt) <mark>Bruckner<\/mark> VI.","fid":"page"}]}]}