{"stem":"telepathisch","instances":[{"docId":"entry__1931-03-29","docUri":"entry__1931-03-29.html","score":1,"contexts":[{"form":"telepathisches","weight":"1","pos":40,"context":"..., dann mit ihnen unten gegessen.― Spirituelles und <mark>telepathisches<\/mark>.― Über ihre Krankheit (die sich hier sehr besserte...","fid":"page"}]},{"docId":"entry__1923-06-07","docUri":"entry__1923-06-07.html","score":1,"contexts":[{"form":"telepathisches","weight":"1","pos":110,"context":"...Dr. Asch, Barjanskis, später Richard. Über <mark>telepathisches<\/mark> u. dgl. (anläßlich Schermann).","fid":"page"}]}]}