{"stem":"wäscherin","instances":[{"docId":"entry__1892-05-21","docUri":"entry__1892-05-21.html","score":1,"contexts":[{"form":"Wäscherin","weight":"1","pos":6,"context":"...21\/5 In Thermidor, wo Mz. die Statistenrolle einer <mark>Wäscherin<\/mark> spielt. Nachher mit ihr, Salten und frère Pfeife...","fid":"p__5"}]},{"docId":"entry__1886-02-01","docUri":"entry__1886-02-01.html","score":1,"contexts":[{"form":"Wäscherin","weight":"1","pos":52,"context":"...Maske einfand, begegnete mir unter andern Fännchen als <mark>Wäscherin<\/mark>, Fanny M. als Deutschmeister, Frl. Kron...","fid":"p__13"}]}]}